odoo/addons/sms_dummy_provider/README.rst
odoo/addons/sms_dummy_provider/__init__.py
odoo/addons/sms_dummy_provider/__manifest__.py
odoo/addons/sms_dummy_provider/i18n/sms_dummy_provider.pot
odoo/addons/sms_dummy_provider/models/__init__.py
odoo/addons/sms_dummy_provider/models/ir_sms_gateway.py
odoo/addons/sms_dummy_provider/readme/CONFIGURE.md
odoo/addons/sms_dummy_provider/readme/CONTRIBUTORS.md
odoo/addons/sms_dummy_provider/readme/DESCRIPTION.md
odoo/addons/sms_dummy_provider/static/description/icon.png
odoo/addons/sms_dummy_provider/static/description/index.html
odoo/addons/sms_dummy_provider/views/ir_sms_gateway.xml
odoo_addon_sms_dummy_provider-16.0.1.0.0.2.dist-info/METADATA
odoo_addon_sms_dummy_provider-16.0.1.0.0.2.dist-info/WHEEL
odoo_addon_sms_dummy_provider-16.0.1.0.0.2.dist-info/top_level.txt
odoo_addon_sms_dummy_provider-16.0.1.0.0.2.dist-info/RECORD
